vietnamadminunits/__init__.py
vietnamadminunits/converter/__init__.py
vietnamadminunits/converter/converter_2025.py
vietnamadminunits/data/converter_2025.json
vietnamadminunits/data/dataset.db
vietnamadminunits/data/parser_from_2025.json
vietnamadminunits/data/parser_legacy.json
vietnamadminunits/database/__init__.py
vietnamadminunits/database/main.py
vietnamadminunits/pandas/__init__.py
vietnamadminunits/pandas/main.py
vietnamadminunits/parser/__init__.py
vietnamadminunits/parser/objects.py
vietnamadminunits/parser/parser_from_2025.py
vietnamadminunits/parser/parser_legacy.py
vietnamadminunits/parser/utils.py
vietnamadminunits-1.0.4.dist-info/licenses/LICENSE
vietnamadminunits-1.0.4.dist-info/METADATA
vietnamadminunits-1.0.4.dist-info/WHEEL
vietnamadminunits-1.0.4.dist-info/top_level.txt
vietnamadminunits-1.0.4.dist-info/RECORD
