Metadata-Version: 2.4
Name: vietnamadminunits
Version: 1.0.4
Summary: Library of standardization and conversion of Vietnamese administrative units
Home-page: https://github.com/tranngocminhhieu/vietnamadminunits
Author: Hieu Tran
Author-email: tnmhieu@gmail.com
Classifier: Programming Language :: Python :: 3
Classifier: Operating System :: OS Independent
Classifier: License :: OSI Approved :: MIT License
Classifier: Topic :: Software Development :: Libraries
Classifier: Intended Audience :: Developers
Classifier: Natural Language :: Vietnamese
Requires-Python: >=3.7
License-File: LICENSE
Requires-Dist: shapely
Requires-Dist: geopy
Requires-Dist: unidecode
Requires-Dist: tqdm
Dynamic: author
Dynamic: author-email
Dynamic: classifier
Dynamic: description
Dynamic: description-content-type
Dynamic: home-page
Dynamic: license-file
Dynamic: requires-dist
Dynamic: requires-python
Dynamic: summary
